pytest_assist/__init__.py
pytest_assist/__main__.py
pytest_assist/export_report.html
pytest_assist/plugin.py
pytest_assist/servers.py
pytest_assist/shared.py
pytest_assist/version.py
pytest_assist/z_dist/func1.js
pytest_assist/z_dist/index.css
pytest_assist/z_dist/index.html
pytest_assist/z_dist/index.js
pytest_assist/z_dist/logo.png
pytest_assist/z_dist/lib/prism.css
pytest_assist/z_dist/lib/prism.js
pytest_assist/z_dist/lib/react-dom.production.min.js
pytest_assist/z_dist/lib/react.production.min.js
pytest_assist-0.1.2.dist-info/LICENSE
pytest_assist-0.1.2.dist-info/METADATA
pytest_assist-0.1.2.dist-info/WHEEL
pytest_assist-0.1.2.dist-info/top_level.txt
pytest_assist-0.1.2.dist-info/RECORD
