Metadata-Version: 2.1
Name: pytest-assist
Version: 0.1.2
Summary: load testing library
Home-page: https://jcyrss.github.io/pytest-assist
Download-URL: https://pypi.python.org/pypi/pytest-assist
Author: byhy
Author-email: jcyrss@gmail.com
License: MIT
Keywords: pytest automation testautomation
Classifier: Intended Audience :: Developers
Classifier: Topic :: Software Development :: Testing
Classifier: License :: OSI Approved :: MIT License
Requires-Python: >=3.8
License-File: LICENSE
Requires-Dist: pytest
Requires-Dist: websockets (>=11.0.3)
